LICENSE
README.md
setup.py
dori_orm/__init__.py
dori_orm/columns.py
dori_orm/db.py
dori_orm/operators.py
dori_orm.egg-info/PKG-INFO
dori_orm.egg-info/SOURCES.txt
dori_orm.egg-info/dependency_links.txt
dori_orm.egg-info/top_level.txt