Metadata-Version: 2.1
Name: dori-orm
Version: 4.6.1
Summary: simple orm, to manage your database.
Home-page: https://github.com/dori-dev/my-orm
Author: Mohammad Dori
Author-email: mr.dori.dev@gmail.com
Classifier: Programming Language :: Python :: 3
Classifier: License :: OSI Approved :: MIT License
Classifier: Operating System :: OS Independent
Requires-Python: >=3.6
License-File: LICENSE
